osom_api/__init__.py
osom_api/__main__.py
osom_api/arguments.py
osom_api/entrypoint.py
osom_api/aio/__init__.py
osom_api/aio/run.py
osom_api/aio/shield_any.py
osom_api/apps/__init__.py
osom_api/apps/bot/__init__.py
osom_api/apps/bot/config.py
osom_api/apps/bot/context.py
osom_api/apps/bot/main.py
osom_api/apps/bot/commands/__init__.py
osom_api/apps/bot/commands/help.py
osom_api/apps/bot/commands/version.py
osom_api/apps/master/__init__.py
osom_api/apps/master/config.py
osom_api/apps/master/context.py
osom_api/apps/master/main.py
osom_api/apps/worker/__init__.py
osom_api/apps/worker/main.py
osom_api/assets/__init__.py
osom_api/chrono/__init__.py
osom_api/chrono/date.py
osom_api/chrono/datetime.py
osom_api/chrono/datetime_filename.py
osom_api/common/__init__.py
osom_api/common/config.py
osom_api/common/context.py
osom_api/crypto/__init__.py
osom_api/crypto/password.py
osom_api/logging/__init__.py
osom_api/logging/access_filter.py
osom_api/logging/clear.py
osom_api/logging/colored_formatter.py
osom_api/logging/logging.py
osom_api/memory/__init__.py
osom_api/memory/shared_memory_queue.py
osom_api/memory/shared_memory_utils.py
osom_api/memory/shared_memory_validator.py
osom_api/mq/__init__.py
osom_api/mq/client.py
osom_api/mq/message.py
osom_api/mq/path.py
osom_api/mq/utils.py
osom_api/random/__init__.py
osom_api/random/hex.py
osom_api/system/__init__.py
osom_api/system/environ.py
osom_api/system/path_context.py
osom_api/types/__init__.py
osom_api/types/string/__init__.py
osom_api/types/string/to_boolean.py
osom_api/uri/__init__.py
osom_api/uri/address_family.py
osom_api/uri/host_port.py
osom_api/uri/rpc_uri.py
osom_api/uri/uds.py
osom_api/www/__init__.py
osom_api-0.0.9.dist-info/LICENSE
osom_api-0.0.9.dist-info/METADATA
osom_api-0.0.9.dist-info/WHEEL
osom_api-0.0.9.dist-info/entry_points.txt
osom_api-0.0.9.dist-info/top_level.txt
osom_api-0.0.9.dist-info/RECORD
